last_common_ancestor.drawio.svg
plantuml_not_convertable.drawio.svg
rebdhuhn/__init__.py
rebdhuhn/_version.py
rebdhuhn/add_watermark.py
rebdhuhn/graph_conversion.py
rebdhuhn/graph_utils.py
rebdhuhn/graphviz.py
rebdhuhn/hochfrequenz-logo.svg
rebdhuhn/kroki.py
rebdhuhn/plantuml.py
rebdhuhn/py.typed
rebdhuhn/utils.py
rebdhuhn/models/__init__.py
rebdhuhn/models/ebd_graph.py
rebdhuhn/models/ebd_table.py
rebdhuhn/models/errors/__init__.py
rebdhuhn-1.0.1.dist-info/METADATA
rebdhuhn-1.0.1.dist-info/WHEEL
rebdhuhn-1.0.1.dist-info/licenses/LICENSE
rebdhuhn-1.0.1.dist-info/RECORD
