Metadata-Version: 2.4
Name: rebdhuhn
Version: 1.0.1
Summary: Converts (already scraped) Entscheidungsbaumdiagramm tables to real graphs
Project-URL: Homepage, https://github.com/Hochfrequenz/rebdhuhn
Project-URL: Changelog, https://github.com/Hochfrequenz/rebdhuhn/releases
Project-URL: Repository, https://github.com/Hochfrequenz/rebdhuhn
Project-URL: Issue-Tracker, https://github.com/Hochfrequenz/rebdhuhn/issues
Author-email: Hochfrequenz Unternehmensberatung GmbH <info@hochfrequenz.de>
License: GPL
License-File: LICENSE
Keywords: ahb,automation,bdew,ebd,edi@energy
Classifier: Development Status :: 5 - Production/Stable
Classifier: Intended Audience :: Developers
Classifier: License :: OSI Approved :: GNU General Public License v3 (GPLv3)
Classifier: Operating System :: OS Independent
Classifier: Programming Language :: Python
Classifier: Programming Language :: Python :: 3 :: Only
Classifier: Programming Language :: Python :: 3.11
Classifier: Programming Language :: Python :: 3.12
Classifier: Programming Language :: Python :: 3.13
Classifier: Programming Language :: Python :: 3.14
Requires-Python: >=3.11
Requires-Dist: lxml>=4.9.3
Requires-Dist: networkx
Requires-Dist: pydantic>=2.0
Requires-Dist: requests
Requires-Dist: svgutils
Provides-Extra: coverage
Requires-Dist: coverage==7.13.0; extra == 'coverage'
Provides-Extra: formatting
Requires-Dist: black==25.12.0; extra == 'formatting'
Requires-Dist: isort==7.0.0; extra == 'formatting'
Provides-Extra: linting
Requires-Dist: pylint==4.0.4; extra == 'linting'
Provides-Extra: packaging
Requires-Dist: build==1.3.0; extra == 'packaging'
Requires-Dist: twine==6.2.0; extra == 'packaging'
Provides-Extra: spellcheck
Requires-Dist: codespell==2.4.1; extra == 'spellcheck'
Provides-Extra: tests
Requires-Dist: pytest==9.0.2; extra == 'tests'
Requires-Dist: syrupy==5.0.0; extra == 'tests'
Requires-Dist: testcontainers>=4.0.0; extra == 'tests'
Provides-Extra: type-check
Requires-Dist: lxml-stubs==0.5.1; extra == 'type-check'
Requires-Dist: mypy==1.19.1; extra == 'type-check'
Requires-Dist: types-docker>=7.0.0; extra == 'type-check'
Requires-Dist: types-requests==2.32.4.20250913; extra == 'type-check'
